akq/__init__.py
akq/cli.py
akq/connections.py
akq/constants.py
akq/cron.py
akq/jobs.py
akq/logs.py
akq/metrics.py
akq/py.typed
akq/typing.py
akq/utils.py
akq/version.py
akq/worker.py
akq-0.0.1.dist-info/LICENSE
akq-0.0.1.dist-info/METADATA
akq-0.0.1.dist-info/WHEEL
akq-0.0.1.dist-info/entry_points.txt
akq-0.0.1.dist-info/top_level.txt
akq-0.0.1.dist-info/zip-safe
akq-0.0.1.dist-info/RECORD
