Metadata-Version: 2.1
Name: akq
Version: 0.0.1
Summary: Job queues in python with asyncio and keydb/redis
Home-page: https://github.com/trisongz/akq
Author: Samuel Colvin, Tri Songz
Author-email: ts@growthengineai.com
License: MIT
Classifier: Development Status :: 4 - Beta
Classifier: Environment :: Console
Classifier: Framework :: AsyncIO
Classifier: Intended Audience :: Developers
Classifier: Intended Audience :: Information Technology
Classifier: Intended Audience :: System Administrators
Classifier: License :: OSI Approved :: MIT License
Classifier: Operating System :: Unix
Classifier: Operating System :: POSIX :: Linux
Classifier: Programming Language :: Python
Classifier: Programming Language :: Python :: 3
Classifier: Programming Language :: Python :: 3 :: Only
Classifier: Programming Language :: Python :: 3.7
Classifier: Programming Language :: Python :: 3.8
Classifier: Programming Language :: Python :: 3.9
Classifier: Programming Language :: Python :: 3.10
Classifier: Topic :: Internet
Classifier: Topic :: Software Development :: Libraries :: Python Modules
Classifier: Topic :: System :: Clustering
Classifier: Topic :: System :: Distributed Computing
Classifier: Topic :: System :: Monitoring
Classifier: Topic :: System :: Systems Administration
Requires-Python: >=3.6
License-File: LICENSE
Requires-Dist: aiokeydb (>=0.0.9)
Requires-Dist: prometheus-client (>=0.14.1)
Requires-Dist: click (>=6.7)
Requires-Dist: pydantic (>=1)
Requires-Dist: typing-extensions (>=3.7) ; python_version < "3.8"
Requires-Dist: dataclasses (>=0.6) ; python_version == "3.6"
Provides-Extra: watch
Requires-Dist: watchgod (>=0.4) ; extra == 'watch'
